{"IxW4bEcczdnwHdaHMGilCg==":"mbr-1920x1080.jpg","O7FXcAja4dcQmIiy4ig0Hw==":"mbr-1620x1080.jpg","xzY5oC1epz+nP8fffJx0Gg==":"mbr-1623x1080.jpg","8US+GhPbXG6y4O6dXqiudw==":"mbr-720x1080.jpg","xuf5rhAWVlgU7mbZHGSYQA==":"mbr-1619x1080.jpg","LHG3KOQjH7L63Ogw0vj50A==":"mbr-1-1620x1080.jpg","JdrUZ6Zf+44jQVq8FwwM8Q==":"mbr-864x1080.jpg","ZELlto1esMhpaR92JZlr/w==":"mbr-1553x1080.jpg","H5m6+5ltu91EhOipiXYRHQ==":"mbr-2-1620x1080.jpg","dhlWWLP6KDEOysfCRmBwAA==":"mbr-3-1620x1080.jpg","1lQf9zKAABlE0c1rlWJekA==":"red-scarlet-1563x1042.jpg","E6yvNIcMHNVu8YlrNrrwsw==":"logo-1920x1080.png","fuoeWz1kxzuU5fnYOcd3Rw==":"qw6jlq-1800x1200.jpg","VI1Sei98uk2fYcZ1KoxDeA==":"image-332x443.jpg","O2u4576p8wZIiAcVvk96Gg==":"image%20(1)-664x458.jpg","Wx5sQd2Kc95Xn/gUsygawQ==":"image%20(2)-670x317.jpg","rYS3QAVnfw+D5JgEblU1DA==":"capture-312x105.png","FjTDCHNWDftnKxi3mVCfig==":"capture-319x162.png","6ff705GifY6OUwHt6RAO9g==":"capture%202-122x107.png","Lf8z9CmpTC10bFh6nBl3Yw==":"capture%202-192x168.png","S4HXF9crqFVfdEHlEIWq5g==":"error-404-566x330.png","2k0330vgXvnn+Q7BdjEj/A==":"mbr-1352x1080.jpg","ZMLpIYPGbc5BFMLQbRjHsw==":"mbr-4-1620x1080.jpg","YhE5LZJDrLuXPHR1ZFiSrg==":"mbr-5-1620x1080.jpg","8SgswqAeMCKhc4lJB9kqsQ==":"image-1-670x448.jpg","3mM2RWdt8FFK1QNFgIpZWg==":"image-4-670x503.jpg","O6DeEWIXVXDEiQNN94RtUg==":"image-3-670x497.jpg","OoxxEnhlQzeHOC500lRNcg==":"image-6-670x872.jpg","kAQ3LZuy1iLRFSXRrzUJdQ==":"image-5-670x1050.jpg","lO/wPW6mBmMTtvJjC5bEXQ==":"3-2-902x505.png","dXrCMzxzGZx56UnklBCpsg==":"error404-640x360.jpg","sCwDxmgaRYOHBY4ighofkg==":"ukulele1-1-500x334.jpg","TZKuL8Scb3ED0g4TQPMMfA==":"capture%203-1256x661.png"}